[
  {
    "RowIndex": 0,
    "Tier": 0,
    "MarkersMultiply": 0.01,
    "Description": ""
  },
  {
    "RowIndex": 1,
    "Tier": 1,
    "MarkersMultiply": 1.0,
    "Description": "valeur : moyenne"
  },
  {
    "RowIndex": 2,
    "Tier": 2,
    "MarkersMultiply": 1.25,
    "Description": "valeur : élevée"
  },
  {
    "RowIndex": 3,
    "Tier": 3,
    "MarkersMultiply": 2.0,
    "Description": "valeur : importante"
  },
  {
    "RowIndex": 4,
    "Tier": 4,
    "MarkersMultiply": 999999.0,
    "Description": "valeur : inestimable"
  }
]