[
  {
    "Id": "Currency",
    "Name": "通貨"
  },
  {
    "Id": "CurrencyQuality",
    "Name": "品質通貨"
  },
  {
    "Id": "CurrencySockets",
    "Name": "工匠的通貨"
  },
  {
    "Id": "Shards",
    "Name": "通貨碎片"
  },
  {
    "Id": "Fragments",
    "Name": "碎片"
  },
  {
    "Id": "FragmentsRitual",
    "Name": "祭祀碎片"
  },
  {
    "Id": "FragmentsUltimatum",
    "Name": "最後通牒碎片"
  },
  {
    "Id": "FragmentsPinnacle",
    "Name": "巔峰碎片"
  },
  {
    "Id": "Essences",
    "Name": "精髓"
  },
  {
    "Id": "EssencesGreater",
    "Name": "高階精髓"
  },
  {
    "Id": "Breach",
    "Name": "裂痕聯盟"
  },
  {
    "Id": "BreachSplinters",
    "Name": "裂痕裂片"
  },
  {
    "Id": "BreachCatalyst",
    "Name": "催化劑"
  },
  {
    "Id": "Delirium",
    "Name": "譫妄異域"
  },
  {
    "Id": "DeliriumSplinters",
    "Name": "幻像異界"
  },
  {
    "Id": "DeliriumInstill",
    "Name": "精練的情感"
  },
  {
    "Id": "DivinationCards",
    "Name": "命運卡"
  },
  {
    "Id": "DivinationCardsWeaponsArmour",
    "Name": "命運卡獎勵武器或護甲"
  },
  {
    "Id": "DivinationCardsJewelleryJewels",
    "Name": "命運卡獎勵飾品或珠寶"
  },
  {
    "Id": "DivinationCardsCurrency",
    "Name": "命運卡獎勵通貨"
  },
  {
    "Id": "DivinationCardsGems",
    "Name": "命運卡獎勵寶石"
  },
  {
    "Id": "DivinationCardsMapsFragments",
    "Name": "命運卡獎勵地圖或碎片"
  },
  {
    "Id": "DivinationCardsFlasks",
    "Name": "命運卡獎勵藥劑"
  },
  {
    "Id": "DivinationCardsMisc",
    "Name": "其他命運卡"
  },
  {
    "Id": "Expedition",
    "Name": "探險聯盟"
  },
  {
    "Id": "Popular",
    "Name": "熱門"
  },
  {
    "Id": "Owned",
    "Name": "已擁有"
  },
  {
    "Id": "Runes",
    "Name": "符文"
  },
  {
    "Id": "Ultimatum",
    "Name": "靈魂核心"
  },
  {
    "Id": "Ritual",
    "Name": "徵兆"
  }
]