[
  {
    "RowIndex": 0,
    "Id": "RedSeeds",
    "BaseItem": {
      "RowIndex": 1650,
      "TableName": "BaseItemTypes",
      "Id": "Metadata/Items/Currency/HarvestSeedRed"
    },
    "Name": "野性結晶生靈之力"
  },
  {
    "RowIndex": 1,
    "Id": "YellowSeeds",
    "BaseItem": {
      "RowIndex": 1651,
      "TableName": "BaseItemTypes",
      "Id": "Metadata/Items/Currency/HarvestSeedGreen"
    },
    "Name": "靈現結晶生靈之力"
  },
  {
    "RowIndex": 2,
    "Id": "BlueSeeds",
    "BaseItem": {
      "RowIndex": 1652,
      "TableName": "BaseItemTypes",
      "Id": "Metadata/Items/Currency/HarvestSeedBlue"
    },
    "Name": "原始結晶生靈之力"
  },
  {
    "RowIndex": 3,
    "Id": "BossSeeds",
    "BaseItem": {
      "RowIndex": 1653,
      "TableName": "BaseItemTypes",
      "Id": "Metadata/Items/Currency/HarvestSeedBoss"
    },
    "Name": "神聖結晶生靈之力"
  }
]