[
  {
    "Id": "Shop",
    "Unk001": [
      128,
      128,
      128
    ],
    "Unk002": [
      255,
      255,
      255
    ],
    "Name": "Tienda"
  },
  {
    "Id": "Pets",
    "Unk001": [
      128,
      128,
      128
    ],
    "Unk002": [
      255,
      255,
      255
    ],
    "Name": "Mascotas"
  },
  {
    "Id": "People",
    "Unk001": [
      128,
      128,
      128
    ],
    "Unk002": [
      255,
      255,
      255
    ],
    "Name": "Personas"
  },
  {
    "Id": "Plants",
    "Unk001": [
      128,
      128,
      128
    ],
    "Unk002": [
      255,
      255,
      255
    ],
    "Name": "Plantas"
  },
  {
    "Id": "Trees",
    "Unk001": [
      128,
      128,
      128
    ],
    "Unk002": [
      255,
      255,
      255
    ],
    "Name": "Árboles"
  },
  {
    "Id": "Nests",
    "Unk001": [
      128,
      128,
      128
    ],
    "Unk002": [
      255,
      255,
      255
    ],
    "Name": "Nidos"
  },
  {
    "Id": "Furniture",
    "Unk001": [
      128,
      128,
      128
    ],
    "Unk002": [
      255,
      255,
      255
    ],
    "Name": "Muebles"
  },
  {
    "Id": "Cages",
    "Unk001": [
      128,
      128,
      128
    ],
    "Unk002": [
      255,
      255,
      255
    ],
    "Name": "Jaulas"
  },
  {
    "Id": "Rocks",
    "Unk001": [
      128,
      128,
      128
    ],
    "Unk002": [
      255,
      255,
      255
    ],
    "Name": "Rocas"
  },
  {
    "Id": "Crates",
    "Unk001": [
      128,
      128,
      128
    ],
    "Unk002": [
      255,
      255,
      255
    ],
    "Name": "Cajas"
  },
  {
    "Id": "Barrels",
    "Unk001": [
      128,
      128,
      128
    ],
    "Unk002": [
      255,
      255,
      255
    ],
    "Name": "Barriles"
  },
  {
    "Id": "Containers",
    "Unk001": [
      128,
      128,
      128
    ],
    "Unk002": [
      255,
      255,
      255
    ],
    "Name": "Contenedores"
  },
  {
    "Id": "Ground",
    "Unk001": [
      128,
      128,
      128
    ],
    "Unk002": [
      255,
      255,
      255
    ],
    "Name": "Suelos"
  },
  {
    "Id": "Water",
    "Unk001": [
      128,
      128,
      128
    ],
    "Unk002": [
      255,
      255,
      255
    ],
    "Name": "Agua"
  },
  {
    "Id": "Walls",
    "Unk001": [
      128,
      128,
      128
    ],
    "Unk002": [
      255,
      255,
      255
    ],
    "Name": "Muros"
  },
  {
    "Id": "Effects",
    "Unk001": [
      128,
      128,
      128
    ],
    "Unk002": [
      255,
      255,
      255
    ],
    "Name": "Efectos"
  },
  {
    "Id": "Weather",
    "Unk001": [
      128,
      128,
      128
    ],
    "Unk002": [
      255,
      255,
      255
    ],
    "Name": "Tiempo"
  },
  {
    "Id": "Lights",
    "Unk001": [
      128,
      128,
      128
    ],
    "Unk002": [
      255,
      255,
      255
    ],
    "Name": "Luces"
  },
  {
    "Id": "Carpets",
    "Unk001": [
      128,
      128,
      128
    ],
    "Unk002": [
      255,
      255,
      255
    ],
    "Name": "Alfombras"
  },
  {
    "Id": "Debris",
    "Unk001": [
      128,
      128,
      128
    ],
    "Unk002": [
      255,
      255,
      255
    ],
    "Name": "Escombros"
  },
  {
    "Id": "Statues",
    "Unk001": [
      128,
      128,
      128
    ],
    "Unk002": [
      255,
      255,
      255
    ],
    "Name": "Estatuas"
  },
  {
    "Id": "Barricades",
    "Unk001": [
      128,
      128,
      128
    ],
    "Unk002": [
      255,
      255,
      255
    ],
    "Name": "Barricadas"
  },
  {
    "Id": "Tents",
    "Unk001": [
      128,
      128,
      128
    ],
    "Unk002": [
      255,
      255,
      255
    ],
    "Name": "Tiendas"
  },
  {
    "Id": "Stalls",
    "Unk001": [
      128,
      128,
      128
    ],
    "Unk002": [
      255,
      255,
      255
    ],
    "Name": "Casetas"
  },
  {
    "Id": "Equipment",
    "Unk001": [
      128,
      128,
      128
    ],
    "Unk002": [
      255,
      255,
      255
    ],
    "Name": "Equipamiento"
  },
  {
    "Id": "Machines",
    "Unk001": [
      128,
      128,
      128
    ],
    "Unk002": [
      255,
      255,
      255
    ],
    "Name": "Máquinas"
  },
  {
    "Id": "Pillars",
    "Unk001": [
      128,
      128,
      128
    ],
    "Unk002": [
      255,
      255,
      255
    ],
    "Name": "Pilares"
  },
  {
    "Id": "Stonework",
    "Unk001": [
      128,
      128,
      128
    ],
    "Unk002": [
      255,
      255,
      255
    ],
    "Name": "Piedra"
  },
  {
    "Id": "Carcasses",
    "Unk001": [
      128,
      128,
      128
    ],
    "Unk002": [
      255,
      255,
      255
    ],
    "Name": "Cadáveres"
  },
  {
    "Id": "Bones",
    "Unk001": [
      128,
      128,
      128
    ],
    "Unk002": [
      255,
      255,
      255
    ],
    "Name": "Huesos"
  },
  {
    "Id": "Vehicles",
    "Unk001": [
      128,
      128,
      128
    ],
    "Unk002": [
      255,
      255,
      255
    ],
    "Name": "Vehículos"
  },
  {
    "Id": "Banners",
    "Unk001": [
      128,
      128,
      128
    ],
    "Unk002": [
      255,
      255,
      255
    ],
    "Name": "Estandartes"
  },
  {
    "Id": "Teleporters",
    "Unk001": [
      128,
      128,
      128
    ],
    "Unk002": [
      255,
      255,
      255
    ],
    "Name": "Teletransportadores"
  },
  {
    "Id": "Games",
    "Unk001": [
      128,
      128,
      128
    ],
    "Unk002": [
      255,
      255,
      255
    ],
    "Name": "Juegos"
  },
  {
    "Id": "MapDevices",
    "Unk001": [
      128,
      128,
      128
    ],
    "Unk002": [
      255,
      255,
      255
    ],
    "Name": "Artefactos de mapas"
  }
]