[
  {
    "Id": 0,
    "Name": "Aspecto para arma"
  },
  {
    "Id": 1,
    "Name": "Aspecto para escudo"
  },
  {
    "Id": 2,
    "Name": "Efecto para arma"
  },
  {
    "Id": 3,
    "Name": "Efecto agregado para arma"
  },
  {
    "Id": 4,
    "Name": "Aspecto para armadura"
  },
  {
    "Id": 5,
    "Name": "Accesorio para armadura"
  },
  {
    "Id": 6,
    "Name": "Aspecto para casco"
  },
  {
    "Id": 7,
    "Name": "Accesorio para casco"
  },
  {
    "Id": 8,
    "Name": "Aspecto para guantes"
  },
  {
    "Id": 9,
    "Name": "Aspecto para botas"
  },
  {
    "Id": 10,
    "Name": "Huellas"
  },
  {
    "Id": 11,
    "Name": "Portal"
  },
  {
    "Id": 12,
    "Name": "Marco social"
  },
  {
    "Id": 13,
    "Name": "Retrato"
  },
  {
    "Id": 14,
    "Name": "Mascota"
  },
  {
    "Id": 15,
    "Name": "Aparición"
  },
  {
    "Id": 16,
    "Name": "Efecto para el personaje"
  },
  {
    "Id": 17,
    "Name": "Efecto para gema de habilidad"
  },
  {
    "Id": 18,
    "Name": "Baile"
  },
  {
    "Id": 19,
    "Name": "Consumible"
  },
  {
    "Id": 20,
    "Name": "Objeto de guarida"
  },
  {
    "Id": 21,
    "Name": "Misceláneo"
  },
  {
    "Id": 22,
    "Name": "Aspecto / Accesorio para casco"
  },
  {
    "Id": 23,
    "Name": "Cursor"
  },
  {
    "Id": 24,
    "Name": "Aspecto para amuleto"
  },
  {
    "Id": 25,
    "Name": "Aspecto para cinturón"
  },
  {
    "Id": 26,
    "Name": "Aspecto para frasco"
  },
  {
    "Id": 27,
    "Name": "Aspecto para joya pasiva"
  },
  {
    "Id": 28,
    "Name": "Aspecto para anillo"
  },
  {
    "Id": 29,
    "Name": "Accesorio para la cadera"
  },
  {
    "Id": 30,
    "Name": "Aspecto alternativo para cargas"
  },
  {
    "Id": 31,
    "Name": "Efecto adicional"
  }
]