[
  {
    "RowIndex": 0,
    "AchievementItemsKey": {
      "RowIndex": 5643,
      "TableName": "AchievementItems"
    },
    "BaseItemTypesKey": {
      "RowIndex": 1942,
      "TableName": "BaseItemTypes"
    },
    "Message": "Earned Korean God Helmet Microtransaction!",
    "Id": "KoreanHat"
  },
  {
    "RowIndex": 1,
    "AchievementItemsKey": {
      "RowIndex": 6819,
      "TableName": "AchievementItems"
    },
    "BaseItemTypesKey": {
      "RowIndex": 1943,
      "TableName": "BaseItemTypes"
    },
    "Message": "Earned Dragon God Hat Microtransaction!",
    "Id": "KoreanHat2"
  }
]