[
  {
    "RowIndex": 0,
    "MonsterLevel": 68,
    "LifeMultiplier": 0
  },
  {
    "RowIndex": 1,
    "MonsterLevel": 69,
    "LifeMultiplier": 0
  },
  {
    "RowIndex": 2,
    "MonsterLevel": 70,
    "LifeMultiplier": 0
  },
  {
    "RowIndex": 3,
    "MonsterLevel": 71,
    "LifeMultiplier": 0
  },
  {
    "RowIndex": 4,
    "MonsterLevel": 72,
    "LifeMultiplier": 0
  },
  {
    "RowIndex": 5,
    "MonsterLevel": 73,
    "LifeMultiplier": 0
  },
  {
    "RowIndex": 6,
    "MonsterLevel": 74,
    "LifeMultiplier": 0
  },
  {
    "RowIndex": 7,
    "MonsterLevel": 75,
    "LifeMultiplier": 0
  },
  {
    "RowIndex": 8,
    "MonsterLevel": 76,
    "LifeMultiplier": 0
  },
  {
    "RowIndex": 9,
    "MonsterLevel": 77,
    "LifeMultiplier": 0
  },
  {
    "RowIndex": 10,
    "MonsterLevel": 78,
    "LifeMultiplier": 0
  },
  {
    "RowIndex": 11,
    "MonsterLevel": 79,
    "LifeMultiplier": 0
  },
  {
    "RowIndex": 12,
    "MonsterLevel": 80,
    "LifeMultiplier": 0
  },
  {
    "RowIndex": 13,
    "MonsterLevel": 81,
    "LifeMultiplier": 0
  },
  {
    "RowIndex": 14,
    "MonsterLevel": 82,
    "LifeMultiplier": 0
  },
  {
    "RowIndex": 15,
    "MonsterLevel": 83,
    "LifeMultiplier": 0
  },
  {
    "RowIndex": 16,
    "MonsterLevel": 84,
    "LifeMultiplier": 0
  },
  {
    "RowIndex": 17,
    "MonsterLevel": 85,
    "LifeMultiplier": 0
  },
  {
    "RowIndex": 18,
    "MonsterLevel": 86,
    "LifeMultiplier": 0
  },
  {
    "RowIndex": 19,
    "MonsterLevel": 87,
    "LifeMultiplier": 0
  },
  {
    "RowIndex": 20,
    "MonsterLevel": 88,
    "LifeMultiplier": 0
  },
  {
    "RowIndex": 21,
    "MonsterLevel": 89,
    "LifeMultiplier": 0
  },
  {
    "RowIndex": 22,
    "MonsterLevel": 90,
    "LifeMultiplier": 0
  }
]