[
  {
    "RowIndex": 0,
    "Id": "Metadata/Items/Currency/CurrencyEssenceLife",
    "StoredItem": {
      "RowIndex": 53,
      "TableName": "BaseItemTypes",
      "Id": "Metadata/Items/Currency/CurrencyEssenceLife"
    },
    "XOffset": 96,
    "YOffset": 170,
    "FirstSlotIndex": 0,
    "Width": 1,
    "Height": 1,
    "IsUpgradableEssenceSlot": true
  },
  {
    "RowIndex": 1,
    "Id": "Metadata/Items/Currency/CurrencyEssenceMana",
    "StoredItem": {
      "RowIndex": 54,
      "TableName": "BaseItemTypes",
      "Id": "Metadata/Items/Currency/CurrencyEssenceMana"
    },
    "XOffset": 181,
    "YOffset": 170,
    "FirstSlotIndex": 1,
    "Width": 1,
    "Height": 1,
    "IsUpgradableEssenceSlot": true
  },
  {
    "RowIndex": 2,
    "Id": "Metadata/Items/Currency/CurrencyEssenceDefences",
    "StoredItem": {
      "RowIndex": 55,
      "TableName": "BaseItemTypes",
      "Id": "Metadata/Items/Currency/CurrencyEssenceDefences"
    },
    "XOffset": 266,
    "YOffset": 170,
    "FirstSlotIndex": 2,
    "Width": 1,
    "Height": 1,
    "IsUpgradableEssenceSlot": true
  },
  {
    "RowIndex": 3,
    "Id": "Metadata/Items/Currency/CurrencyEssencePhysical",
    "StoredItem": {
      "RowIndex": 56,
      "TableName": "BaseItemTypes",
      "Id": "Metadata/Items/Currency/CurrencyEssencePhysical"
    },
    "XOffset": 96,
    "YOffset": 260,
    "FirstSlotIndex": 3,
    "Width": 1,
    "Height": 1,
    "IsUpgradableEssenceSlot": true
  },
  {
    "RowIndex": 4,
    "Id": "Metadata/Items/Currency/CurrencyEssenceFire",
    "StoredItem": {
      "RowIndex": 57,
      "TableName": "BaseItemTypes",
      "Id": "Metadata/Items/Currency/CurrencyEssenceFire"
    },
    "XOffset": 181,
    "YOffset": 260,
    "FirstSlotIndex": 4,
    "Width": 1,
    "Height": 1,
    "IsUpgradableEssenceSlot": true
  },
  {
    "RowIndex": 5,
    "Id": "Metadata/Items/Currency/CurrencyEssenceCold",
    "StoredItem": {
      "RowIndex": 58,
      "TableName": "BaseItemTypes",
      "Id": "Metadata/Items/Currency/CurrencyEssenceCold"
    },
    "XOffset": 266,
    "YOffset": 260,
    "FirstSlotIndex": 5,
    "Width": 1,
    "Height": 1,
    "IsUpgradableEssenceSlot": true
  },
  {
    "RowIndex": 6,
    "Id": "Metadata/Items/Currency/CurrencyEssenceLightning",
    "StoredItem": {
      "RowIndex": 59,
      "TableName": "BaseItemTypes",
      "Id": "Metadata/Items/Currency/CurrencyEssenceLightning"
    },
    "XOffset": 96,
    "YOffset": 350,
    "FirstSlotIndex": 6,
    "Width": 1,
    "Height": 1,
    "IsUpgradableEssenceSlot": true
  },
  {
    "RowIndex": 7,
    "Id": "Metadata/Items/Currency/CurrencyEssenceChaos",
    "StoredItem": {
      "RowIndex": 60,
      "TableName": "BaseItemTypes",
      "Id": "Metadata/Items/Currency/CurrencyEssenceChaos"
    },
    "XOffset": 181,
    "YOffset": 350,
    "FirstSlotIndex": 7,
    "Width": 1,
    "Height": 1,
    "IsUpgradableEssenceSlot": true
  },
  {
    "RowIndex": 8,
    "Id": "Metadata/Items/Currency/CurrencyEssenceAttack",
    "StoredItem": {
      "RowIndex": 61,
      "TableName": "BaseItemTypes",
      "Id": "Metadata/Items/Currency/CurrencyEssenceAttack"
    },
    "XOffset": 266,
    "YOffset": 350,
    "FirstSlotIndex": 8,
    "Width": 1,
    "Height": 1,
    "IsUpgradableEssenceSlot": true
  },
  {
    "RowIndex": 9,
    "Id": "Metadata/Items/Currency/CurrencyEssenceCaster",
    "StoredItem": {
      "RowIndex": 62,
      "TableName": "BaseItemTypes",
      "Id": "Metadata/Items/Currency/CurrencyEssenceCaster"
    },
    "XOffset": 96,
    "YOffset": 440,
    "FirstSlotIndex": 9,
    "Width": 1,
    "Height": 1,
    "IsUpgradableEssenceSlot": true
  },
  {
    "RowIndex": 10,
    "Id": "Metadata/Items/Currency/CurrencyEssenceSpeed",
    "StoredItem": {
      "RowIndex": 63,
      "TableName": "BaseItemTypes",
      "Id": "Metadata/Items/Currency/CurrencyEssenceSpeed"
    },
    "XOffset": 181,
    "YOffset": 440,
    "FirstSlotIndex": 10,
    "Width": 1,
    "Height": 1,
    "IsUpgradableEssenceSlot": true
  },
  {
    "RowIndex": 11,
    "Id": "Metadata/Items/Currency/CurrencyEssenceAttribute",
    "StoredItem": {
      "RowIndex": 64,
      "TableName": "BaseItemTypes",
      "Id": "Metadata/Items/Currency/CurrencyEssenceAttribute"
    },
    "XOffset": 266,
    "YOffset": 440,
    "FirstSlotIndex": 11,
    "Width": 1,
    "Height": 1,
    "IsUpgradableEssenceSlot": true
  },
  {
    "RowIndex": 12,
    "Id": "Metadata/Items/Currency/CurrencyGreaterEssenceLife",
    "StoredItem": {
      "RowIndex": 65,
      "TableName": "BaseItemTypes",
      "Id": "Metadata/Items/Currency/CurrencyGreaterEssenceLife"
    },
    "XOffset": 606,
    "YOffset": 170,
    "FirstSlotIndex": 12,
    "Width": 1,
    "Height": 1,
    "IsUpgradableEssenceSlot": true
  },
  {
    "RowIndex": 13,
    "Id": "Metadata/Items/Currency/CurrencyGreaterEssenceMana",
    "StoredItem": {
      "RowIndex": 66,
      "TableName": "BaseItemTypes",
      "Id": "Metadata/Items/Currency/CurrencyGreaterEssenceMana"
    },
    "XOffset": 691,
    "YOffset": 170,
    "FirstSlotIndex": 13,
    "Width": 1,
    "Height": 1,
    "IsUpgradableEssenceSlot": true
  },
  {
    "RowIndex": 14,
    "Id": "Metadata/Items/Currency/CurrencyGreaterEssenceDefences",
    "StoredItem": {
      "RowIndex": 67,
      "TableName": "BaseItemTypes",
      "Id": "Metadata/Items/Currency/CurrencyGreaterEssenceDefences"
    },
    "XOffset": 776,
    "YOffset": 170,
    "FirstSlotIndex": 14,
    "Width": 1,
    "Height": 1,
    "IsUpgradableEssenceSlot": true
  },
  {
    "RowIndex": 15,
    "Id": "Metadata/Items/Currency/CurrencyGreaterEssencePhysical",
    "StoredItem": {
      "RowIndex": 68,
      "TableName": "BaseItemTypes",
      "Id": "Metadata/Items/Currency/CurrencyGreaterEssencePhysical"
    },
    "XOffset": 606,
    "YOffset": 260,
    "FirstSlotIndex": 15,
    "Width": 1,
    "Height": 1,
    "IsUpgradableEssenceSlot": true
  },
  {
    "RowIndex": 16,
    "Id": "Metadata/Items/Currency/CurrencyGreaterEssenceFire",
    "StoredItem": {
      "RowIndex": 69,
      "TableName": "BaseItemTypes",
      "Id": "Metadata/Items/Currency/CurrencyGreaterEssenceFire"
    },
    "XOffset": 691,
    "YOffset": 260,
    "FirstSlotIndex": 16,
    "Width": 1,
    "Height": 1,
    "IsUpgradableEssenceSlot": true
  },
  {
    "RowIndex": 17,
    "Id": "Metadata/Items/Currency/CurrencyGreaterEssenceCold",
    "StoredItem": {
      "RowIndex": 70,
      "TableName": "BaseItemTypes",
      "Id": "Metadata/Items/Currency/CurrencyGreaterEssenceCold"
    },
    "XOffset": 776,
    "YOffset": 260,
    "FirstSlotIndex": 17,
    "Width": 1,
    "Height": 1,
    "IsUpgradableEssenceSlot": true
  },
  {
    "RowIndex": 18,
    "Id": "Metadata/Items/Currency/CurrencyGreaterEssenceLightning",
    "StoredItem": {
      "RowIndex": 71,
      "TableName": "BaseItemTypes",
      "Id": "Metadata/Items/Currency/CurrencyGreaterEssenceLightning"
    },
    "XOffset": 606,
    "YOffset": 350,
    "FirstSlotIndex": 18,
    "Width": 1,
    "Height": 1,
    "IsUpgradableEssenceSlot": true
  },
  {
    "RowIndex": 19,
    "Id": "Metadata/Items/Currency/CurrencyGreaterEssenceChaos",
    "StoredItem": {
      "RowIndex": 72,
      "TableName": "BaseItemTypes",
      "Id": "Metadata/Items/Currency/CurrencyGreaterEssenceChaos"
    },
    "XOffset": 691,
    "YOffset": 350,
    "FirstSlotIndex": 19,
    "Width": 1,
    "Height": 1,
    "IsUpgradableEssenceSlot": true
  },
  {
    "RowIndex": 20,
    "Id": "Metadata/Items/Currency/CurrencyGreaterEssenceAttack",
    "StoredItem": {
      "RowIndex": 73,
      "TableName": "BaseItemTypes",
      "Id": "Metadata/Items/Currency/CurrencyGreaterEssenceAttack"
    },
    "XOffset": 776,
    "YOffset": 350,
    "FirstSlotIndex": 20,
    "Width": 1,
    "Height": 1,
    "IsUpgradableEssenceSlot": true
  },
  {
    "RowIndex": 21,
    "Id": "Metadata/Items/Currency/CurrencyGreaterEssenceCaster",
    "StoredItem": {
      "RowIndex": 74,
      "TableName": "BaseItemTypes",
      "Id": "Metadata/Items/Currency/CurrencyGreaterEssenceCaster"
    },
    "XOffset": 606,
    "YOffset": 440,
    "FirstSlotIndex": 21,
    "Width": 1,
    "Height": 1,
    "IsUpgradableEssenceSlot": true
  },
  {
    "RowIndex": 22,
    "Id": "Metadata/Items/Currency/CurrencyGreaterEssenceSpeed",
    "StoredItem": {
      "RowIndex": 75,
      "TableName": "BaseItemTypes",
      "Id": "Metadata/Items/Currency/CurrencyGreaterEssenceSpeed"
    },
    "XOffset": 691,
    "YOffset": 440,
    "FirstSlotIndex": 22,
    "Width": 1,
    "Height": 1,
    "IsUpgradableEssenceSlot": true
  },
  {
    "RowIndex": 23,
    "Id": "Metadata/Items/Currency/CurrencyGreaterEssenceAttribute",
    "StoredItem": {
      "RowIndex": 76,
      "TableName": "BaseItemTypes",
      "Id": "Metadata/Items/Currency/CurrencyGreaterEssenceAttribute"
    },
    "XOffset": 776,
    "YOffset": 440,
    "FirstSlotIndex": 23,
    "Width": 1,
    "Height": 1,
    "IsUpgradableEssenceSlot": true
  },
  {
    "RowIndex": 24,
    "Id": "CraftingSlot",
    "StoredItem": null,
    "XOffset": 418,
    "YOffset": 360,
    "FirstSlotIndex": 24,
    "Width": 2,
    "Height": 4,
    "IsUpgradableEssenceSlot": true
  },
  {
    "RowIndex": 25,
    "Id": "Generic1",
    "StoredItem": null,
    "XOffset": 309,
    "YOffset": 620,
    "FirstSlotIndex": 26,
    "Width": 1,
    "Height": 1,
    "IsUpgradableEssenceSlot": true
  },
  {
    "RowIndex": 26,
    "Id": "Generic2",
    "StoredItem": null,
    "XOffset": 394,
    "YOffset": 620,
    "FirstSlotIndex": 27,
    "Width": 1,
    "Height": 1,
    "IsUpgradableEssenceSlot": true
  },
  {
    "RowIndex": 27,
    "Id": "Generic3",
    "StoredItem": null,
    "XOffset": 479,
    "YOffset": 620,
    "FirstSlotIndex": 28,
    "Width": 1,
    "Height": 1,
    "IsUpgradableEssenceSlot": true
  },
  {
    "RowIndex": 28,
    "Id": "Generic4",
    "StoredItem": null,
    "XOffset": 564,
    "YOffset": 620,
    "FirstSlotIndex": 29,
    "Width": 1,
    "Height": 1,
    "IsUpgradableEssenceSlot": true
  }
]