[
  {
    "Item": {
      "RowIndex": 722,
      "TableName": null
    },
    "IndexAs": {
      "RowIndex": 721,
      "TableName": null
    }
  },
  {
    "Item": {
      "RowIndex": 723,
      "TableName": null
    },
    "IndexAs": {
      "RowIndex": 721,
      "TableName": null
    }
  },
  {
    "Item": {
      "RowIndex": 724,
      "TableName": null
    },
    "IndexAs": {
      "RowIndex": 721,
      "TableName": null
    }
  },
  {
    "Item": {
      "RowIndex": 726,
      "TableName": null
    },
    "IndexAs": {
      "RowIndex": 725,
      "TableName": null
    }
  },
  {
    "Item": {
      "RowIndex": 727,
      "TableName": null
    },
    "IndexAs": {
      "RowIndex": 725,
      "TableName": null
    }
  },
  {
    "Item": {
      "RowIndex": 729,
      "TableName": null
    },
    "IndexAs": {
      "RowIndex": 728,
      "TableName": null
    }
  },
  {
    "Item": {
      "RowIndex": 730,
      "TableName": null
    },
    "IndexAs": {
      "RowIndex": 728,
      "TableName": null
    }
  },
  {
    "Item": {
      "RowIndex": 732,
      "TableName": null
    },
    "IndexAs": {
      "RowIndex": 731,
      "TableName": null
    }
  },
  {
    "Item": {
      "RowIndex": 734,
      "TableName": null
    },
    "IndexAs": {
      "RowIndex": 733,
      "TableName": null
    }
  },
  {
    "Item": {
      "RowIndex": 735,
      "TableName": null
    },
    "IndexAs": {
      "RowIndex": 733,
      "TableName": null
    }
  },
  {
    "Item": {
      "RowIndex": 737,
      "TableName": null
    },
    "IndexAs": {
      "RowIndex": 736,
      "TableName": null
    }
  },
  {
    "Item": {
      "RowIndex": 738,
      "TableName": null
    },
    "IndexAs": {
      "RowIndex": 736,
      "TableName": null
    }
  },
  {
    "Item": {
      "RowIndex": 740,
      "TableName": null
    },
    "IndexAs": {
      "RowIndex": 739,
      "TableName": null
    }
  },
  {
    "Item": {
      "RowIndex": 741,
      "TableName": null
    },
    "IndexAs": {
      "RowIndex": 739,
      "TableName": null
    }
  },
  {
    "Item": {
      "RowIndex": 742,
      "TableName": null
    },
    "IndexAs": {
      "RowIndex": 739,
      "TableName": null
    }
  }
]