[
  {
    "RowIndex": 0,
    "Id": "UniqueChestTest1",
    "WordsKey": {
      "RowIndex": 360,
      "TableName": "Words",
      "Text": " DO NOT USE"
    },
    "FlavourTextKey": {
      "RowIndex": 665,
      "TableName": "FlavourText",
      "Id": "WIP"
    },
    "MinLevel": 0,
    "ModsKeys": [],
    "SpawnWeight": 0,
    "Unk006": [],
    "AOFile": "Metadata/Chests/StrongBoxes/ArmoryStrongBox.ao",
    "Unk008": false,
    "Unk009": [],
    "AppearanceChestsKey": null,
    "ChestsKey": {
      "RowIndex": 98,
      "TableName": "Chests",
      "Id": "Metadata/Chests/StrongBoxes/Strongbox"
    },
    "Unk012": []
  },
  {
    "RowIndex": 1,
    "Id": "PerandusBank",
    "WordsKey": {
      "RowIndex": 366,
      "TableName": "Words",
      "Text": "Perandus Bank"
    },
    "FlavourTextKey": {
      "RowIndex": 382,
      "TableName": "FlavourText",
      "Id": "UniqueChest1"
    },
    "MinLevel": 20,
    "ModsKeys": [
      {
        "RowIndex": 6370,
        "TableName": "Mods",
        "Id": "ChestSpawnRogueExileUniqueChest1"
      },
      {
        "RowIndex": 6358,
        "TableName": "Mods",
        "Id": "ChestDropJeweleryUniqueUniqueChest1"
      },
      {
        "RowIndex": 6405,
        "TableName": "Mods",
        "Id": "ChestExtraMagicItemsUniqueChest1"
      },
      {
        "RowIndex": 6411,
        "TableName": "Mods",
        "Id": "ChestExtraRareItemsUniqueChest1"
      },
      {
        "RowIndex": 6628,
        "TableName": "Mods",
        "Id": "UniqueChestNoRegularDrops"
      }
    ],
    "SpawnWeight": 0,
    "Unk006": [],
    "AOFile": "Metadata/Chests/StrongBoxes/PerandusBox.ao",
    "Unk008": false,
    "Unk009": [],
    "AppearanceChestsKey": null,
    "ChestsKey": {
      "RowIndex": 93,
      "TableName": "Chests",
      "Id": "Metadata/Chests/StrongBoxes/Jeweller"
    },
    "Unk012": [
      {
        "RowIndex": 9179,
        "TableName": null
      }
    ]
  },
  {
    "RowIndex": 2,
    "Id": "KaomsCache",
    "WordsKey": {
      "RowIndex": 367,
      "TableName": "Words",
      "Text": "Kaom's Cache"
    },
    "FlavourTextKey": {
      "RowIndex": 383,
      "TableName": "FlavourText",
      "Id": "UniqueChest2"
    },
    "MinLevel": 20,
    "ModsKeys": [
      {
        "RowIndex": 6361,
        "TableName": "Mods",
        "Id": "ChestSummonRaresUniqueChest2"
      },
      {
        "RowIndex": 6355,
        "TableName": "Mods",
        "Id": "ChestDropKaomsUniqueUniqueChest2"
      },
      {
        "RowIndex": 6383,
        "TableName": "Mods",
        "Id": "ChestKaomsTotemsUniqueChest2"
      },
      {
        "RowIndex": 6410,
        "TableName": "Mods",
        "Id": "ChestExtraRareItemsUniqueChest2"
      },
      {
        "RowIndex": 6628,
        "TableName": "Mods",
        "Id": "UniqueChestNoRegularDrops"
      }
    ],
    "SpawnWeight": 60,
    "Unk006": [],
    "AOFile": "Metadata/Chests/StrongBoxes/KaomBox.ao",
    "Unk008": false,
    "Unk009": [],
    "AppearanceChestsKey": null,
    "ChestsKey": {
      "RowIndex": 80,
      "TableName": "Chests",
      "Id": "Metadata/Chests/StrongBoxes/Armory"
    },
    "Unk012": [
      {
        "RowIndex": 9179,
        "TableName": null
      }
    ]
  },
  {
    "RowIndex": 3,
    "Id": "EmpyreanApparatus",
    "WordsKey": {
      "RowIndex": 368,
      "TableName": "Words",
      "Text": "Empyrean Apparatus"
    },
    "FlavourTextKey": {
      "RowIndex": 384,
      "TableName": "FlavourText",
      "Id": "UniqueChest3"
    },
    "MinLevel": 60,
    "ModsKeys": [
      {
        "RowIndex": 6362,
        "TableName": "Mods",
        "Id": "ChestSummonRaresUniqueChest3"
      },
      {
        "RowIndex": 6356,
        "TableName": "Mods",
        "Id": "ChestDropMapsUniqueUniqueChest3"
      },
      {
        "RowIndex": 6418,
        "TableName": "Mods",
        "Id": "ChestItemQualityUniqueChest3"
      },
      {
        "RowIndex": 6628,
        "TableName": "Mods",
        "Id": "UniqueChestNoRegularDrops"
      }
    ],
    "SpawnWeight": 40,
    "Unk006": [],
    "AOFile": "Metadata/Chests/StrongBoxes/MalachaisBox.ao",
    "Unk008": false,
    "Unk009": [],
    "AppearanceChestsKey": null,
    "ChestsKey": {
      "RowIndex": 83,
      "TableName": "Chests",
      "Id": "Metadata/Chests/StrongBoxes/Cartographer"
    },
    "Unk012": [
      {
        "RowIndex": 9179,
        "TableName": null
      }
    ]
  },
  {
    "RowIndex": 4,
    "Id": "ObaChest1",
    "WordsKey": {
      "RowIndex": 406,
      "TableName": "Words",
      "Text": "Oba's Prized Cache"
    },
    "FlavourTextKey": {
      "RowIndex": 423,
      "TableName": "FlavourText",
      "Id": "UniqueChestMap9"
    },
    "MinLevel": 0,
    "ModsKeys": [
      {
        "RowIndex": 6409,
        "TableName": "Mods",
        "Id": "ChestExtraRareItemsUniqueChestMap9"
      },
      {
        "RowIndex": 6406,
        "TableName": "Mods",
        "Id": "ChestExtraMagicItemsUniqueChestMap9_"
      }
    ],
    "SpawnWeight": 0,
    "Unk006": [],
    "AOFile": "Metadata/Chests/StrongBoxes/JewellerStrongBox.ao",
    "Unk008": false,
    "Unk009": [],
    "AppearanceChestsKey": null,
    "ChestsKey": {
      "RowIndex": 93,
      "TableName": "Chests",
      "Id": "Metadata/Chests/StrongBoxes/Jeweller"
    },
    "Unk012": [
      {
        "RowIndex": 9179,
        "TableName": null
      }
    ]
  },
  {
    "RowIndex": 5,
    "Id": "ObaChest2",
    "WordsKey": {
      "RowIndex": 407,
      "TableName": "Words",
      "Text": "Oba's Riches"
    },
    "FlavourTextKey": {
      "RowIndex": 423,
      "TableName": "FlavourText",
      "Id": "UniqueChestMap9"
    },
    "MinLevel": 0,
    "ModsKeys": [
      {
        "RowIndex": 6399,
        "TableName": "Mods",
        "Id": "ChestExtraNormalItemsUniqueChestMap9b"
      }
    ],
    "SpawnWeight": 0,
    "Unk006": [],
    "AOFile": "Metadata/Chests/StrongBoxes/ArcanistStrongBox.ao",
    "Unk008": false,
    "Unk009": [],
    "AppearanceChestsKey": null,
    "ChestsKey": {
      "RowIndex": 77,
      "TableName": "Chests",
      "Id": "Metadata/Chests/StrongBoxes/Arcanist"
    },
    "Unk012": [
      {
        "RowIndex": 9179,
        "TableName": null
      }
    ]
  },
  {
    "RowIndex": 6,
    "Id": "ObaChest3",
    "WordsKey": {
      "RowIndex": 408,
      "TableName": "Words",
      "Text": "Oba's Glittering Stash"
    },
    "FlavourTextKey": {
      "RowIndex": 423,
      "TableName": "FlavourText",
      "Id": "UniqueChestMap9"
    },
    "MinLevel": 0,
    "ModsKeys": [
      {
        "RowIndex": 6398,
        "TableName": "Mods",
        "Id": "ChestExtraNormalItemsUniqueChestMap9"
      },
      {
        "RowIndex": 6419,
        "TableName": "Mods",
        "Id": "ChestItemQualityUniqueChestMap9"
      }
    ],
    "SpawnWeight": 0,
    "Unk006": [],
    "AOFile": "Metadata/Chests/StrongBoxes/GemcutterStrongBox.ao",
    "Unk008": false,
    "Unk009": [],
    "AppearanceChestsKey": null,
    "ChestsKey": {
      "RowIndex": 91,
      "TableName": "Chests",
      "Id": "Metadata/Chests/StrongBoxes/Gemcutter"
    },
    "Unk012": [
      {
        "RowIndex": 9179,
        "TableName": null
      }
    ]
  },
  {
    "RowIndex": 7,
    "Id": "GrandmasterGemcutters",
    "WordsKey": {
      "RowIndex": 447,
      "TableName": "Words",
      "Text": "Grandmaster's Gemcutting Cache"
    },
    "FlavourTextKey": {
      "RowIndex": 459,
      "TableName": "FlavourText",
      "Id": "UniqueChestGrandmaster1"
    },
    "MinLevel": 0,
    "ModsKeys": [
      {
        "RowIndex": 6420,
        "TableName": "Mods",
        "Id": "ChestItemQualityGrandmasterGemcutterChest1"
      },
      {
        "RowIndex": 6394,
        "TableName": "Mods",
        "Id": "ChestGemsExperienceGrandmasterGemcutterChest1"
      },
      {
        "RowIndex": 6402,
        "TableName": "Mods",
        "Id": "ChestExtraNormalItemsGrandmasterGemcutterChest1"
      },
      {
        "RowIndex": 6965,
        "TableName": "Mods",
        "Id": "DisablePartyScalingForChests"
      }
    ],
    "SpawnWeight": 0,
    "Unk006": [],
    "AOFile": "Metadata/Chests/StrongBoxes/OrnateStrongbox.ao",
    "Unk008": true,
    "Unk009": [],
    "AppearanceChestsKey": null,
    "ChestsKey": {
      "RowIndex": 92,
      "TableName": "Chests",
      "Id": "Metadata/Chests/StrongBoxes/GemcutterGrandmaster"
    },
    "Unk012": []
  },
  {
    "RowIndex": 8,
    "Id": "GrandmasterArcanists",
    "WordsKey": {
      "RowIndex": 448,
      "TableName": "Words",
      "Text": "Grandmaster's Arcanist Cache"
    },
    "FlavourTextKey": {
      "RowIndex": 459,
      "TableName": "FlavourText",
      "Id": "UniqueChestGrandmaster1"
    },
    "MinLevel": 0,
    "ModsKeys": [
      {
        "RowIndex": 6403,
        "TableName": "Mods",
        "Id": "ChestExtraNormalItemsGrandmasterArcanistChest1_"
      },
      {
        "RowIndex": 6965,
        "TableName": "Mods",
        "Id": "DisablePartyScalingForChests"
      }
    ],
    "SpawnWeight": 0,
    "Unk006": [],
    "AOFile": "Metadata/Chests/StrongBoxes/OrnateStrongbox.ao",
    "Unk008": true,
    "Unk009": [],
    "AppearanceChestsKey": null,
    "ChestsKey": {
      "RowIndex": 79,
      "TableName": "Chests",
      "Id": "Metadata/Chests/StrongBoxes/ArcanistGrandmaster"
    },
    "Unk012": []
  },
  {
    "RowIndex": 9,
    "Id": "GrandmasterCartographers",
    "WordsKey": {
      "RowIndex": 449,
      "TableName": "Words",
      "Text": "Grandmaster's Cartography Cache"
    },
    "FlavourTextKey": {
      "RowIndex": 459,
      "TableName": "FlavourText",
      "Id": "UniqueChestGrandmaster1"
    },
    "MinLevel": 0,
    "ModsKeys": [
      {
        "RowIndex": 6401,
        "TableName": "Mods",
        "Id": "ChestExtraNormalItemsGrandmasterCartographerChest1"
      },
      {
        "RowIndex": 6407,
        "TableName": "Mods",
        "Id": "ChestExtraMagicItemsGrandmasterCartographerChest1"
      },
      {
        "RowIndex": 6413,
        "TableName": "Mods",
        "Id": "ChestExtraRareItemsGrandmasterCartographerChest1"
      },
      {
        "RowIndex": 6421,
        "TableName": "Mods",
        "Id": "ChestItemQualityGrandmasterCartographerChest1"
      },
      {
        "RowIndex": 6965,
        "TableName": "Mods",
        "Id": "DisablePartyScalingForChests"
      }
    ],
    "SpawnWeight": 0,
    "Unk006": [],
    "AOFile": "Metadata/Chests/StrongBoxes/OrnateStrongbox.ao",
    "Unk008": true,
    "Unk009": [],
    "AppearanceChestsKey": null,
    "ChestsKey": {
      "RowIndex": 88,
      "TableName": "Chests",
      "Id": "Metadata/Chests/StrongBoxes/CartographerGrandmaster"
    },
    "Unk012": []
  },
  {
    "RowIndex": 10,
    "Id": "GrandmasterOrnateStrongbox",
    "WordsKey": {
      "RowIndex": 450,
      "TableName": "Words",
      "Text": "Grandmaster's Ornate Cache"
    },
    "FlavourTextKey": {
      "RowIndex": 459,
      "TableName": "FlavourText",
      "Id": "UniqueChestGrandmaster1"
    },
    "MinLevel": 0,
    "ModsKeys": [
      {
        "RowIndex": 6341,
        "TableName": "Mods",
        "Id": "ChestItemRarityGrandmasterOrnateChest1"
      },
      {
        "RowIndex": 6333,
        "TableName": "Mods",
        "Id": "ChestItemQuantityGrandmasterOrnateChest1"
      },
      {
        "RowIndex": 6412,
        "TableName": "Mods",
        "Id": "ChestExtraRareItemsGrandmasterOrnateChest1"
      },
      {
        "RowIndex": 6965,
        "TableName": "Mods",
        "Id": "DisablePartyScalingForChests"
      },
      {
        "RowIndex": 6434,
        "TableName": "Mods",
        "Id": "ChestItemLevelGrandmasterGeneric"
      }
    ],
    "SpawnWeight": 0,
    "Unk006": [],
    "AOFile": "Metadata/Chests/StrongBoxes/OrnateStrongbox.ao",
    "Unk008": true,
    "Unk009": [],
    "AppearanceChestsKey": null,
    "ChestsKey": {
      "RowIndex": 97,
      "TableName": "Chests",
      "Id": "Metadata/Chests/StrongBoxes/OrnateGrandmaster"
    },
    "Unk012": []
  },
  {
    "RowIndex": 11,
    "Id": "GrandmasterUniqueItem",
    "WordsKey": {
      "RowIndex": 451,
      "TableName": "Words",
      "Text": "Grandmaster's Treasury"
    },
    "FlavourTextKey": {
      "RowIndex": 459,
      "TableName": "FlavourText",
      "Id": "UniqueChestGrandmaster1"
    },
    "MinLevel": 0,
    "ModsKeys": [
      {
        "RowIndex": 6352,
        "TableName": "Mods",
        "Id": "ChestDropUniqueGrandmasterUniqueChest1"
      },
      {
        "RowIndex": 6335,
        "TableName": "Mods",
        "Id": "ChestItemQuantityGrandmasterUniqueChest1"
      },
      {
        "RowIndex": 6343,
        "TableName": "Mods",
        "Id": "ChestItemRarityGrandmasterUniqueChest1"
      },
      {
        "RowIndex": 6965,
        "TableName": "Mods",
        "Id": "DisablePartyScalingForChests"
      },
      {
        "RowIndex": 6434,
        "TableName": "Mods",
        "Id": "ChestItemLevelGrandmasterGeneric"
      }
    ],
    "SpawnWeight": 0,
    "Unk006": [],
    "AOFile": "Metadata/Chests/StrongBoxes/OrnateStrongbox.ao",
    "Unk008": true,
    "Unk009": [],
    "AppearanceChestsKey": null,
    "ChestsKey": {
      "RowIndex": 99,
      "TableName": "Chests",
      "Id": "Metadata/Chests/StrongBoxes/StrongboxGrandmaster"
    },
    "Unk012": []
  },
  {
    "RowIndex": 12,
    "Id": "GrandmasterSameBaseType",
    "WordsKey": {
      "RowIndex": 452,
      "TableName": "Words",
      "Text": "Grandmaster's Trove"
    },
    "FlavourTextKey": {
      "RowIndex": 459,
      "TableName": "FlavourText",
      "Id": "UniqueChestGrandmaster1"
    },
    "MinLevel": 0,
    "ModsKeys": [
      {
        "RowIndex": 6335,
        "TableName": "Mods",
        "Id": "ChestItemQuantityGrandmasterUniqueChest1"
      },
      {
        "RowIndex": 6343,
        "TableName": "Mods",
        "Id": "ChestItemRarityGrandmasterUniqueChest1"
      },
      {
        "RowIndex": 7192,
        "TableName": "Mods",
        "Id": "ChestRaresSameBaseTypeGrandmasterChest1"
      },
      {
        "RowIndex": 6965,
        "TableName": "Mods",
        "Id": "DisablePartyScalingForChests"
      },
      {
        "RowIndex": 6434,
        "TableName": "Mods",
        "Id": "ChestItemLevelGrandmasterGeneric"
      }
    ],
    "SpawnWeight": 0,
    "Unk006": [],
    "AOFile": "Metadata/Chests/StrongBoxes/OrnateStrongbox.ao",
    "Unk008": true,
    "Unk009": [],
    "AppearanceChestsKey": null,
    "ChestsKey": {
      "RowIndex": 99,
      "TableName": "Chests",
      "Id": "Metadata/Chests/StrongBoxes/StrongboxGrandmaster"
    },
    "Unk012": []
  },
  {
    "RowIndex": 13,
    "Id": "GrandmasterVaalVessel",
    "WordsKey": {
      "RowIndex": 453,
      "TableName": "Words",
      "Text": "Grandmaster's Corrupted Cache"
    },
    "FlavourTextKey": {
      "RowIndex": 459,
      "TableName": "FlavourText",
      "Id": "UniqueChestGrandmaster1"
    },
    "MinLevel": 0,
    "ModsKeys": [
      {
        "RowIndex": 6444,
        "TableName": "Mods",
        "Id": "ChestExtraVaalGemsGrandmasterVaalChest1"
      },
      {
        "RowIndex": 6335,
        "TableName": "Mods",
        "Id": "ChestItemQuantityGrandmasterUniqueChest1"
      },
      {
        "RowIndex": 6343,
        "TableName": "Mods",
        "Id": "ChestItemRarityGrandmasterUniqueChest1"
      },
      {
        "RowIndex": 7188,
        "TableName": "Mods",
        "Id": "ChestExtraVaalFragmentsGrandmasterChest1"
      },
      {
        "RowIndex": 6965,
        "TableName": "Mods",
        "Id": "DisablePartyScalingForChests"
      },
      {
        "RowIndex": 6434,
        "TableName": "Mods",
        "Id": "ChestItemLevelGrandmasterGeneric"
      }
    ],
    "SpawnWeight": 0,
    "Unk006": [],
    "AOFile": "Metadata/Chests/StrongBoxes/OrnateStrongbox.ao",
    "Unk008": true,
    "Unk009": [],
    "AppearanceChestsKey": null,
    "ChestsKey": {
      "RowIndex": 99,
      "TableName": "Chests",
      "Id": "Metadata/Chests/StrongBoxes/StrongboxGrandmaster"
    },
    "Unk012": []
  },
  {
    "RowIndex": 14,
    "Id": "GrandmasterLargeStrongbox",
    "WordsKey": {
      "RowIndex": 454,
      "TableName": "Words",
      "Text": "Grandmaster's Large Cache"
    },
    "FlavourTextKey": {
      "RowIndex": 459,
      "TableName": "FlavourText",
      "Id": "UniqueChestGrandmaster1"
    },
    "MinLevel": 0,
    "ModsKeys": [
      {
        "RowIndex": 6342,
        "TableName": "Mods",
        "Id": "ChestItemRarityGrandmasterLargeChest1"
      },
      {
        "RowIndex": 6334,
        "TableName": "Mods",
        "Id": "ChestItemQuantityGrandmasterLargeChest1"
      },
      {
        "RowIndex": 6965,
        "TableName": "Mods",
        "Id": "DisablePartyScalingForChests"
      },
      {
        "RowIndex": 6434,
        "TableName": "Mods",
        "Id": "ChestItemLevelGrandmasterGeneric"
      }
    ],
    "SpawnWeight": 0,
    "Unk006": [],
    "AOFile": "Metadata/Chests/StrongBoxes/OrnateStrongbox.ao",
    "Unk008": true,
    "Unk009": [],
    "AppearanceChestsKey": null,
    "ChestsKey": {
      "RowIndex": 95,
      "TableName": "Chests",
      "Id": "Metadata/Chests/StrongBoxes/LargeGrandmaster"
    },
    "Unk012": []
  },
  {
    "RowIndex": 15,
    "Id": "BarrelOfSpiders",
    "WordsKey": {
      "RowIndex": 459,
      "TableName": "Words",
      "Text": "Strange Barrel"
    },
    "FlavourTextKey": {
      "RowIndex": 464,
      "TableName": "FlavourText",
      "Id": "UniqueChestBarrel1"
    },
    "MinLevel": 30,
    "ModsKeys": [
      {
        "RowIndex": 7253,
        "TableName": "Mods",
        "Id": "BarrelOfSpidersDaemon"
      },
      {
        "RowIndex": 6451,
        "TableName": "Mods",
        "Id": "ChestBarrelOfSpidersUnique"
      },
      {
        "RowIndex": 6391,
        "TableName": "Mods",
        "Id": "ChestPoisonCloudBarrelOfSpiders"
      }
    ],
    "SpawnWeight": 100,
    "Unk006": [],
    "AOFile": "Metadata/Chests/Barrels/GenericBarrel01.ao",
    "Unk008": true,
    "Unk009": [],
    "AppearanceChestsKey": {
      "RowIndex": 364,
      "TableName": "Chests",
      "Id": "Metadata/Chests/DelveChests/FrigidFossilChest"
    },
    "ChestsKey": {
      "RowIndex": 98,
      "TableName": "Chests",
      "Id": "Metadata/Chests/StrongBoxes/Strongbox"
    },
    "Unk012": [
      {
        "RowIndex": 9179,
        "TableName": null
      }
    ]
  },
  {
    "RowIndex": 16,
    "Id": "DeshretsStorm",
    "WordsKey": {
      "RowIndex": 671,
      "TableName": "Words",
      "Text": "Deshret's Storm"
    },
    "FlavourTextKey": {
      "RowIndex": 840,
      "TableName": "FlavourText",
      "Id": "UniqueChest4"
    },
    "MinLevel": 35,
    "ModsKeys": [
      {
        "RowIndex": 8444,
        "TableName": "Mods",
        "Id": "ChestDroppedWeaponsAnimate"
      },
      {
        "RowIndex": 6375,
        "TableName": "Mods",
        "Id": "ChestSpawnContinuousSandstormDaemon"
      },
      {
        "RowIndex": 8446,
        "TableName": "Mods",
        "Id": "ChestDropMarakethWeapons"
      },
      {
        "RowIndex": 6431,
        "TableName": "Mods",
        "Id": "ChestItemLinksUniqueChest4"
      },
      {
        "RowIndex": 6427,
        "TableName": "Mods",
        "Id": "ChestItemSocketsUniqueChest4"
      }
    ],
    "SpawnWeight": 100,
    "Unk006": [],
    "AOFile": "Metadata/Chests/UniqueStrongboxes/Vase.ao",
    "Unk008": false,
    "Unk009": [],
    "AppearanceChestsKey": null,
    "ChestsKey": {
      "RowIndex": 81,
      "TableName": "Chests",
      "Id": "Metadata/Chests/StrongBoxes/Arsenal"
    },
    "Unk012": [
      {
        "RowIndex": 9179,
        "TableName": null
      }
    ]
  },
  {
    "RowIndex": 17,
    "Id": "AshesOfTheCondemned",
    "WordsKey": {
      "RowIndex": 672,
      "TableName": "Words",
      "Text": "Ashes of the Condemned"
    },
    "FlavourTextKey": {
      "RowIndex": 841,
      "TableName": "FlavourText",
      "Id": "UniqueChest5"
    },
    "MinLevel": 40,
    "ModsKeys": [
      {
        "RowIndex": 6363,
        "TableName": "Mods",
        "Id": "ChestSummonRaresUniqueChest4"
      },
      {
        "RowIndex": 6374,
        "TableName": "Mods",
        "Id": "ChestSpawnContinuousTormentSpirits"
      },
      {
        "RowIndex": 6336,
        "TableName": "Mods",
        "Id": "ChestItemQuantityUniqueChest5"
      },
      {
        "RowIndex": 6347,
        "TableName": "Mods",
        "Id": "ChestItemRarityUniqueChest5"
      }
    ],
    "SpawnWeight": 100,
    "Unk006": [],
    "AOFile": "Metadata/Chests/UniqueStrongboxes/BaroqueVase.ao",
    "Unk008": false,
    "Unk009": [],
    "AppearanceChestsKey": null,
    "ChestsKey": {
      "RowIndex": 98,
      "TableName": "Chests",
      "Id": "Metadata/Chests/StrongBoxes/Strongbox"
    },
    "Unk012": [
      {
        "RowIndex": 9179,
        "TableName": null
      }
    ]
  },
  {
    "RowIndex": 18,
    "Id": "MutewindCache",
    "WordsKey": {
      "RowIndex": 673,
      "TableName": "Words",
      "Text": "Mutewind Cache"
    },
    "FlavourTextKey": {
      "RowIndex": 842,
      "TableName": "FlavourText",
      "Id": "UniqueChest6"
    },
    "MinLevel": 56,
    "ModsKeys": [
      {
        "RowIndex": 6377,
        "TableName": "Mods",
        "Id": "ChestSpawnColdWarband"
      },
      {
        "RowIndex": 8441,
        "TableName": "Mods",
        "Id": "ChestDropColdWarbandUnique"
      },
      {
        "RowIndex": 6337,
        "TableName": "Mods",
        "Id": "ChestItemQuantityUniqueChest6"
      },
      {
        "RowIndex": 6435,
        "TableName": "Mods",
        "Id": "ChestItemLevelUniqueChest6"
      }
    ],
    "SpawnWeight": 30,
    "Unk006": [],
    "AOFile": "Metadata/Chests/UniqueStrongboxes/ChestMetal.ao",
    "Unk008": false,
    "Unk009": [],
    "AppearanceChestsKey": null,
    "ChestsKey": {
      "RowIndex": 98,
      "TableName": "Chests",
      "Id": "Metadata/Chests/StrongBoxes/Strongbox"
    },
    "Unk012": [
      {
        "RowIndex": 9179,
        "TableName": null
      }
    ]
  },
  {
    "RowIndex": 19,
    "Id": "RedbladeCache",
    "WordsKey": {
      "RowIndex": 674,
      "TableName": "Words",
      "Text": "Redblade Cache"
    },
    "FlavourTextKey": {
      "RowIndex": 843,
      "TableName": "FlavourText",
      "Id": "UniqueChest7"
    },
    "MinLevel": 56,
    "ModsKeys": [
      {
        "RowIndex": 6376,
        "TableName": "Mods",
        "Id": "ChestSpawnFireWarband"
      },
      {
        "RowIndex": 8440,
        "TableName": "Mods",
        "Id": "ChestDropFireWarbandUnique"
      },
      {
        "RowIndex": 6337,
        "TableName": "Mods",
        "Id": "ChestItemQuantityUniqueChest6"
      },
      {
        "RowIndex": 6435,
        "TableName": "Mods",
        "Id": "ChestItemLevelUniqueChest6"
      }
    ],
    "SpawnWeight": 30,
    "Unk006": [],
    "AOFile": "Metadata/Chests/UniqueStrongboxes/ChestMetal.ao",
    "Unk008": false,
    "Unk009": [],
    "AppearanceChestsKey": null,
    "ChestsKey": {
      "RowIndex": 98,
      "TableName": "Chests",
      "Id": "Metadata/Chests/StrongBoxes/Strongbox"
    },
    "Unk012": [
      {
        "RowIndex": 9179,
        "TableName": null
      }
    ]
  },
  {
    "RowIndex": 20,
    "Id": "BrinerotCache",
    "WordsKey": {
      "RowIndex": 675,
      "TableName": "Words",
      "Text": "Brinerot Cache"
    },
    "FlavourTextKey": {
      "RowIndex": 844,
      "TableName": "FlavourText",
      "Id": "UniqueChest8"
    },
    "MinLevel": 56,
    "ModsKeys": [
      {
        "RowIndex": 6378,
        "TableName": "Mods",
        "Id": "ChestSpawnLightningWarband"
      },
      {
        "RowIndex": 8442,
        "TableName": "Mods",
        "Id": "ChestDropLightningWarbandUnique"
      },
      {
        "RowIndex": 6337,
        "TableName": "Mods",
        "Id": "ChestItemQuantityUniqueChest6"
      },
      {
        "RowIndex": 6435,
        "TableName": "Mods",
        "Id": "ChestItemLevelUniqueChest6"
      }
    ],
    "SpawnWeight": 30,
    "Unk006": [],
    "AOFile": "Metadata/Chests/UniqueStrongboxes/ChestMetal.ao",
    "Unk008": false,
    "Unk009": [],
    "AppearanceChestsKey": null,
    "ChestsKey": {
      "RowIndex": 98,
      "TableName": "Chests",
      "Id": "Metadata/Chests/StrongBoxes/Strongbox"
    },
    "Unk012": [
      {
        "RowIndex": 9179,
        "TableName": null
      }
    ]
  },
  {
    "RowIndex": 21,
    "Id": "RenegadesCache",
    "WordsKey": {
      "RowIndex": 676,
      "TableName": "Words",
      "Text": "Renegades Cache"
    },
    "FlavourTextKey": {
      "RowIndex": 845,
      "TableName": "FlavourText",
      "Id": "UniqueChest9"
    },
    "MinLevel": 56,
    "ModsKeys": [
      {
        "RowIndex": 6379,
        "TableName": "Mods",
        "Id": "ChestSpawnChaosWarband"
      },
      {
        "RowIndex": 8443,
        "TableName": "Mods",
        "Id": "ChestDropChaosWarbandUnique_"
      },
      {
        "RowIndex": 6337,
        "TableName": "Mods",
        "Id": "ChestItemQuantityUniqueChest6"
      },
      {
        "RowIndex": 6435,
        "TableName": "Mods",
        "Id": "ChestItemLevelUniqueChest6"
      }
    ],
    "SpawnWeight": 10,
    "Unk006": [],
    "AOFile": "Metadata/Chests/UniqueStrongboxes/ChestMetal.ao",
    "Unk008": false,
    "Unk009": [],
    "AppearanceChestsKey": null,
    "ChestsKey": {
      "RowIndex": 98,
      "TableName": "Chests",
      "Id": "Metadata/Chests/StrongBoxes/Strongbox"
    },
    "Unk012": [
      {
        "RowIndex": 9179,
        "TableName": null
      }
    ]
  },
  {
    "RowIndex": 22,
    "Id": "ProphecyWickedKing4",
    "WordsKey": {
      "RowIndex": 776,
      "TableName": "Words",
      "Text": "The Plaguemaw's Offering"
    },
    "FlavourTextKey": {
      "RowIndex": 1028,
      "TableName": "FlavourText",
      "Id": "ProphecyWickedKingChest"
    },
    "MinLevel": 0,
    "ModsKeys": [
      {
        "RowIndex": 6400,
        "TableName": "Mods",
        "Id": "ChestExtraNormalItemsProphecyWickedKing4"
      }
    ],
    "SpawnWeight": 0,
    "Unk006": [],
    "AOFile": "Metadata/Chests/UniqueStrongboxes/ChestMetal.ao",
    "Unk008": false,
    "Unk009": [],
    "AppearanceChestsKey": null,
    "ChestsKey": {
      "RowIndex": 78,
      "TableName": "Chests",
      "Id": "Metadata/Chests/StrongBoxes/ArcanistProphecy"
    },
    "Unk012": [
      {
        "RowIndex": 9179,
        "TableName": null
      }
    ]
  },
  {
    "RowIndex": 23,
    "Id": "VaultsOfAtziriUnique",
    "WordsKey": {
      "RowIndex": 799,
      "TableName": "Words",
      "Text": "Atziri's Vessel"
    },
    "FlavourTextKey": {
      "RowIndex": 1050,
      "TableName": "FlavourText",
      "Id": "AtzirisVessel"
    },
    "MinLevel": 0,
    "ModsKeys": [
      {
        "RowIndex": 6965,
        "TableName": "Mods",
        "Id": "DisablePartyScalingForChests"
      }
    ],
    "SpawnWeight": 0,
    "Unk006": [],
    "AOFile": "Metadata/Chests/VaalChests/VaalGoldChest02.ao",
    "Unk008": true,
    "Unk009": [],
    "AppearanceChestsKey": null,
    "ChestsKey": {
      "RowIndex": 102,
      "TableName": "Chests",
      "Id": "Metadata/Chests/StrongBoxes/VaultsOfAtziriUniqueChest"
    },
    "Unk012": []
  },
  {
    "RowIndex": 24,
    "Id": "BreachUniqueBox",
    "WordsKey": {
      "RowIndex": 801,
      "TableName": "Words",
      "Text": "Breach Box"
    },
    "FlavourTextKey": {
      "RowIndex": 1059,
      "TableName": "FlavourText",
      "Id": "BeachBox"
    },
    "MinLevel": 0,
    "ModsKeys": [
      {
        "RowIndex": 6399,
        "TableName": "Mods",
        "Id": "ChestExtraNormalItemsUniqueChestMap9b"
      }
    ],
    "SpawnWeight": 0,
    "Unk006": [],
    "AOFile": "Metadata/Chests/Breach/BreachChestLarge.ao",
    "Unk008": true,
    "Unk009": [],
    "AppearanceChestsKey": null,
    "ChestsKey": {
      "RowIndex": 117,
      "TableName": "Chests",
      "Id": "Metadata/Chests/StrongBoxes/StrongboxBreach1"
    },
    "Unk012": []
  },
  {
    "RowIndex": 25,
    "Id": "DivinationCardUniqueBox",
    "WordsKey": {
      "RowIndex": 856,
      "TableName": "Words",
      "Text": "The Maelstrom Cell"
    },
    "FlavourTextKey": {
      "RowIndex": 847,
      "TableName": "FlavourText",
      "Id": "UniqueChest12"
    },
    "MinLevel": 0,
    "ModsKeys": [
      {
        "RowIndex": 7263,
        "TableName": "Mods",
        "Id": "UniqueDivStrongboxBossDaemon"
      },
      {
        "RowIndex": 6452,
        "TableName": "Mods",
        "Id": "ChestSpecificDivinationCardsUnique__1"
      },
      {
        "RowIndex": 6628,
        "TableName": "Mods",
        "Id": "UniqueChestNoRegularDrops"
      }
    ],
    "SpawnWeight": 0,
    "Unk006": [],
    "AOFile": "Metadata/Chests/UniqueStrongboxes/DivinationCardUniqueStrongbox.ao",
    "Unk008": true,
    "Unk009": [],
    "AppearanceChestsKey": null,
    "ChestsKey": {
      "RowIndex": 1184,
      "TableName": "Chests",
      "Id": "Metadata/Chests/StrongBoxes/StrongboxDivinationShaper"
    },
    "Unk012": [
      {
        "RowIndex": 9179,
        "TableName": null
      }
    ]
  },
  {
    "RowIndex": 26,
    "Id": "WeylamsWarChest",
    "WordsKey": {
      "RowIndex": 867,
      "TableName": "Words",
      "Text": "Weylam's War Chest"
    },
    "FlavourTextKey": {
      "RowIndex": 846,
      "TableName": "FlavourText",
      "Id": "UniqueChest10"
    },
    "MinLevel": 40,
    "ModsKeys": [
      {
        "RowIndex": 6404,
        "TableName": "Mods",
        "Id": "ChestExtraNormalItemsUnique__1"
      },
      {
        "RowIndex": 7259,
        "TableName": "Mods",
        "Id": "WeylamsWarChestDaemon"
      },
      {
        "RowIndex": 8977,
        "TableName": "Mods",
        "Id": "PirateChestUniques__1"
      },
      {
        "RowIndex": 9037,
        "TableName": "Mods",
        "Id": "WeylamsWarChestDisplay"
      }
    ],
    "SpawnWeight": 60,
    "Unk006": [],
    "AOFile": "Metadata/Chests/UniqueStrongboxes/WarChest.ao",
    "Unk008": false,
    "Unk009": [],
    "AppearanceChestsKey": null,
    "ChestsKey": {
      "RowIndex": 77,
      "TableName": "Chests",
      "Id": "Metadata/Chests/StrongBoxes/Arcanist"
    },
    "Unk012": [
      {
        "RowIndex": 9179,
        "TableName": null
      }
    ]
  },
  {
    "RowIndex": 27,
    "Id": "ForgottenReliquaryChest",
    "WordsKey": {
      "RowIndex": 892,
      "TableName": "Words",
      "Text": "Legacy Relic"
    },
    "FlavourTextKey": {
      "RowIndex": 1188,
      "TableName": "FlavourText",
      "Id": "ChestForgottenReliquary"
    },
    "MinLevel": 0,
    "ModsKeys": [
      {
        "RowIndex": 9009,
        "TableName": "Mods",
        "Id": "ChestDropReliquaryItemsLegacy"
      }
    ],
    "SpawnWeight": 0,
    "Unk006": [],
    "AOFile": "Metadata/Chests/CopperChests/ClassicVault.ao",
    "Unk008": true,
    "Unk009": [],
    "AppearanceChestsKey": null,
    "ChestsKey": {
      "RowIndex": 131,
      "TableName": "Chests",
      "Id": "Metadata/Chests/Legacy/ForgottenReliquary"
    },
    "Unk012": []
  },
  {
    "RowIndex": 28,
    "Id": "ForgottenReliquaryChest2",
    "WordsKey": {
      "RowIndex": 893,
      "TableName": "Words",
      "Text": "Timeworn Relic"
    },
    "FlavourTextKey": {
      "RowIndex": 1189,
      "TableName": "FlavourText",
      "Id": "ChestForgottenReliquary2"
    },
    "MinLevel": 0,
    "ModsKeys": [
      {
        "RowIndex": 9010,
        "TableName": "Mods",
        "Id": "ChestDropReliquaryItems340"
      }
    ],
    "SpawnWeight": 0,
    "Unk006": [],
    "AOFile": "Metadata/Chests/CopperChests/ClassicVault.ao",
    "Unk008": true,
    "Unk009": [],
    "AppearanceChestsKey": null,
    "ChestsKey": {
      "RowIndex": 132,
      "TableName": "Chests",
      "Id": "Metadata/Chests/Legacy/ForgottenReliquary2"
    },
    "Unk012": []
  },
  {
    "RowIndex": 29,
    "Id": "ForgottenReliquaryChestVaal",
    "WordsKey": {
      "RowIndex": 894,
      "TableName": "Words",
      "Text": "Vaal Relic"
    },
    "FlavourTextKey": {
      "RowIndex": 1190,
      "TableName": "FlavourText",
      "Id": "ChestForgottenReliquaryVaal"
    },
    "MinLevel": 0,
    "ModsKeys": [
      {
        "RowIndex": 9011,
        "TableName": "Mods",
        "Id": "ChestDropReliquaryItemsVaal"
      }
    ],
    "SpawnWeight": 0,
    "Unk006": [],
    "AOFile": "Metadata/Chests/CopperChests/ClassicVault.ao",
    "Unk008": true,
    "Unk009": [],
    "AppearanceChestsKey": null,
    "ChestsKey": {
      "RowIndex": 133,
      "TableName": "Chests",
      "Id": "Metadata/Chests/Legacy/ForgottenReliquaryVaal"
    },
    "Unk012": []
  },
  {
    "RowIndex": 30,
    "Id": "ForgottenReliquaryVenarius",
    "WordsKey": {
      "RowIndex": 895,
      "TableName": "Words",
      "Text": "Forgotten Relic"
    },
    "FlavourTextKey": {
      "RowIndex": 1191,
      "TableName": "FlavourText",
      "Id": "ChestForgottenReliquaryVenarius"
    },
    "MinLevel": 0,
    "ModsKeys": [
      {
        "RowIndex": 9012,
        "TableName": "Mods",
        "Id": "ChestDropReliquaryItemsVenarius"
      }
    ],
    "SpawnWeight": 0,
    "Unk006": [],
    "AOFile": "Metadata/Chests/CopperChests/ClassicVault.ao",
    "Unk008": true,
    "Unk009": [],
    "AppearanceChestsKey": null,
    "ChestsKey": {
      "RowIndex": 134,
      "TableName": "Chests",
      "Id": "Metadata/Chests/Legacy/ForgottenReliquaryVenarius"
    },
    "Unk012": []
  },
  {
    "RowIndex": 31,
    "Id": "ForgottenReliquaryEaterOfWorlds",
    "WordsKey": {
      "RowIndex": 896,
      "TableName": "Words",
      "Text": "Visceral Relic"
    },
    "FlavourTextKey": {
      "RowIndex": 1192,
      "TableName": "FlavourText",
      "Id": "ChestForgottenReliquaryEaterOfWorlds"
    },
    "MinLevel": 0,
    "ModsKeys": [
      {
        "RowIndex": 9013,
        "TableName": "Mods",
        "Id": "ChestDropReliquaryItemsEaterOfWorlds"
      }
    ],
    "SpawnWeight": 0,
    "Unk006": [],
    "AOFile": "Metadata/Chests/CopperChests/ClassicVault.ao",
    "Unk008": true,
    "Unk009": [],
    "AppearanceChestsKey": null,
    "ChestsKey": {
      "RowIndex": 135,
      "TableName": "Chests",
      "Id": "Metadata/Chests/Legacy/ForgottenReliquaryEaterOfWorlds"
    },
    "Unk012": []
  },
  {
    "RowIndex": 32,
    "Id": "ForgottenReliquaryMaven",
    "WordsKey": {
      "RowIndex": 897,
      "TableName": "Words",
      "Text": "Shiny Relic"
    },
    "FlavourTextKey": {
      "RowIndex": 1193,
      "TableName": "FlavourText",
      "Id": "ChestForgottenReliquaryMaven"
    },
    "MinLevel": 0,
    "ModsKeys": [
      {
        "RowIndex": 9014,
        "TableName": "Mods",
        "Id": "ChestDropReliquaryItemsMaven"
      }
    ],
    "SpawnWeight": 0,
    "Unk006": [],
    "AOFile": "Metadata/Chests/CopperChests/ClassicVault.ao",
    "Unk008": true,
    "Unk009": [],
    "AppearanceChestsKey": null,
    "ChestsKey": {
      "RowIndex": 136,
      "TableName": "Chests",
      "Id": "Metadata/Chests/Legacy/ForgottenReliquaryMaven"
    },
    "Unk012": []
  },
  {
    "RowIndex": 33,
    "Id": "ForgottenReliquarySearingExarch",
    "WordsKey": {
      "RowIndex": 898,
      "TableName": "Words",
      "Text": "Archive Relic"
    },
    "FlavourTextKey": {
      "RowIndex": 1194,
      "TableName": "FlavourText",
      "Id": "ChestForgottenReliquarySearingExarch"
    },
    "MinLevel": 0,
    "ModsKeys": [
      {
        "RowIndex": 9015,
        "TableName": "Mods",
        "Id": "ChestDropReliquaryItemsSearingExarch"
      }
    ],
    "SpawnWeight": 0,
    "Unk006": [],
    "AOFile": "Metadata/Chests/CopperChests/ClassicVault.ao",
    "Unk008": true,
    "Unk009": [],
    "AppearanceChestsKey": null,
    "ChestsKey": {
      "RowIndex": 137,
      "TableName": "Chests",
      "Id": "Metadata/Chests/Legacy/ForgottenReliquarySearingExarch"
    },
    "Unk012": []
  },
  {
    "RowIndex": 34,
    "Id": "ForgottenReliquarySirus",
    "WordsKey": {
      "RowIndex": 899,
      "TableName": "Words",
      "Text": "Oubliette Relic"
    },
    "FlavourTextKey": {
      "RowIndex": 1195,
      "TableName": "FlavourText",
      "Id": "ChestForgottenReliquarySirus"
    },
    "MinLevel": 0,
    "ModsKeys": [
      {
        "RowIndex": 9016,
        "TableName": "Mods",
        "Id": "ChestDropReliquaryItemsSirus"
      }
    ],
    "SpawnWeight": 0,
    "Unk006": [],
    "AOFile": "Metadata/Chests/CopperChests/ClassicVault.ao",
    "Unk008": true,
    "Unk009": [],
    "AppearanceChestsKey": null,
    "ChestsKey": {
      "RowIndex": 138,
      "TableName": "Chests",
      "Id": "Metadata/Chests/Legacy/ForgottenReliquarySirus"
    },
    "Unk012": []
  },
  {
    "RowIndex": 35,
    "Id": "ForgottenReliquaryShaper",
    "WordsKey": {
      "RowIndex": 900,
      "TableName": "Words",
      "Text": "Cosmic Relic"
    },
    "FlavourTextKey": {
      "RowIndex": 1196,
      "TableName": "FlavourText",
      "Id": "ChestForgottenReliquaryUberShaper"
    },
    "MinLevel": 0,
    "ModsKeys": [
      {
        "RowIndex": 9017,
        "TableName": "Mods",
        "Id": "ChestDropReliquaryItemsShaper"
      }
    ],
    "SpawnWeight": 0,
    "Unk006": [],
    "AOFile": "Metadata/Chests/CopperChests/ClassicVault.ao",
    "Unk008": true,
    "Unk009": [],
    "AppearanceChestsKey": null,
    "ChestsKey": {
      "RowIndex": 139,
      "TableName": "Chests",
      "Id": "Metadata/Chests/Legacy/ForgottenReliquaryShaper"
    },
    "Unk012": []
  },
  {
    "RowIndex": 36,
    "Id": "ForgottenReliquaryUberElder",
    "WordsKey": {
      "RowIndex": 901,
      "TableName": "Words",
      "Text": "Decaying Relic"
    },
    "FlavourTextKey": {
      "RowIndex": 1197,
      "TableName": "FlavourText",
      "Id": "ChestForgottenReliquaryUberUberElder"
    },
    "MinLevel": 0,
    "ModsKeys": [
      {
        "RowIndex": 9018,
        "TableName": "Mods",
        "Id": "ChestDropReliquaryItemsUberElder"
      }
    ],
    "SpawnWeight": 0,
    "Unk006": [],
    "AOFile": "Metadata/Chests/CopperChests/ClassicVault.ao",
    "Unk008": true,
    "Unk009": [],
    "AppearanceChestsKey": null,
    "ChestsKey": {
      "RowIndex": 140,
      "TableName": "Chests",
      "Id": "Metadata/Chests/Legacy/ForgottenReliquaryUberElder"
    },
    "Unk012": []
  },
  {
    "RowIndex": 37,
    "Id": "ForgottenReliquaryCosmic",
    "WordsKey": {
      "RowIndex": 902,
      "TableName": "Words",
      "Text": "Voidborn Relic"
    },
    "FlavourTextKey": {
      "RowIndex": 1198,
      "TableName": "FlavourText",
      "Id": "ChestForgottenReliquaryCosmic"
    },
    "MinLevel": 0,
    "ModsKeys": [
      {
        "RowIndex": 9019,
        "TableName": "Mods",
        "Id": "ChestDropReliquaryItemsCosmic"
      }
    ],
    "SpawnWeight": 0,
    "Unk006": [],
    "AOFile": "Metadata/Chests/Legacy/ForgottenReliquaryCosmic.ao",
    "Unk008": true,
    "Unk009": [],
    "AppearanceChestsKey": null,
    "ChestsKey": {
      "RowIndex": 141,
      "TableName": "Chests",
      "Id": "Metadata/Chests/Legacy/ForgottenReliquaryCosmic"
    },
    "Unk012": []
  },
  {
    "RowIndex": 38,
    "Id": "EmpyreanApparatus2",
    "WordsKey": {
      "RowIndex": 368,
      "TableName": "Words",
      "Text": "Empyrean Apparatus"
    },
    "FlavourTextKey": {
      "RowIndex": 384,
      "TableName": "FlavourText",
      "Id": "UniqueChest3"
    },
    "MinLevel": 68,
    "ModsKeys": [
      {
        "RowIndex": 6362,
        "TableName": "Mods",
        "Id": "ChestSummonRaresUniqueChest3"
      },
      {
        "RowIndex": 6356,
        "TableName": "Mods",
        "Id": "ChestDropMapsUniqueUniqueChest3"
      },
      {
        "RowIndex": 6418,
        "TableName": "Mods",
        "Id": "ChestItemQualityUniqueChest3"
      },
      {
        "RowIndex": 6628,
        "TableName": "Mods",
        "Id": "UniqueChestNoRegularDrops"
      }
    ],
    "SpawnWeight": 40,
    "Unk006": [],
    "AOFile": "Metadata/Chests/StrongBoxes/MalachaisBox.ao",
    "Unk008": false,
    "Unk009": [],
    "AppearanceChestsKey": null,
    "ChestsKey": {
      "RowIndex": 84,
      "TableName": "Chests",
      "Id": "Metadata/Chests/StrongBoxes/CartographerLowMaps"
    },
    "Unk012": [
      {
        "RowIndex": 9179,
        "TableName": null
      }
    ]
  },
  {
    "RowIndex": 39,
    "Id": "EmpyreanApparatus3",
    "WordsKey": {
      "RowIndex": 368,
      "TableName": "Words",
      "Text": "Empyrean Apparatus"
    },
    "FlavourTextKey": {
      "RowIndex": 384,
      "TableName": "FlavourText",
      "Id": "UniqueChest3"
    },
    "MinLevel": 72,
    "ModsKeys": [
      {
        "RowIndex": 6362,
        "TableName": "Mods",
        "Id": "ChestSummonRaresUniqueChest3"
      },
      {
        "RowIndex": 6356,
        "TableName": "Mods",
        "Id": "ChestDropMapsUniqueUniqueChest3"
      },
      {
        "RowIndex": 6418,
        "TableName": "Mods",
        "Id": "ChestItemQualityUniqueChest3"
      },
      {
        "RowIndex": 6628,
        "TableName": "Mods",
        "Id": "UniqueChestNoRegularDrops"
      }
    ],
    "SpawnWeight": 40,
    "Unk006": [],
    "AOFile": "Metadata/Chests/StrongBoxes/MalachaisBox.ao",
    "Unk008": false,
    "Unk009": [],
    "AppearanceChestsKey": null,
    "ChestsKey": {
      "RowIndex": 85,
      "TableName": "Chests",
      "Id": "Metadata/Chests/StrongBoxes/CartographerMidMaps"
    },
    "Unk012": [
      {
        "RowIndex": 9179,
        "TableName": null
      }
    ]
  },
  {
    "RowIndex": 40,
    "Id": "EmpyreanApparatus4",
    "WordsKey": {
      "RowIndex": 368,
      "TableName": "Words",
      "Text": "Empyrean Apparatus"
    },
    "FlavourTextKey": {
      "RowIndex": 384,
      "TableName": "FlavourText",
      "Id": "UniqueChest3"
    },
    "MinLevel": 76,
    "ModsKeys": [
      {
        "RowIndex": 6362,
        "TableName": "Mods",
        "Id": "ChestSummonRaresUniqueChest3"
      },
      {
        "RowIndex": 6356,
        "TableName": "Mods",
        "Id": "ChestDropMapsUniqueUniqueChest3"
      },
      {
        "RowIndex": 6418,
        "TableName": "Mods",
        "Id": "ChestItemQualityUniqueChest3"
      },
      {
        "RowIndex": 6628,
        "TableName": "Mods",
        "Id": "UniqueChestNoRegularDrops"
      }
    ],
    "SpawnWeight": 40,
    "Unk006": [],
    "AOFile": "Metadata/Chests/StrongBoxes/MalachaisBox.ao",
    "Unk008": false,
    "Unk009": [],
    "AppearanceChestsKey": null,
    "ChestsKey": {
      "RowIndex": 86,
      "TableName": "Chests",
      "Id": "Metadata/Chests/StrongBoxes/CartographerHighMaps"
    },
    "Unk012": [
      {
        "RowIndex": 9179,
        "TableName": null
      }
    ]
  },
  {
    "RowIndex": 41,
    "Id": "EmpyreanApparatus5",
    "WordsKey": {
      "RowIndex": 368,
      "TableName": "Words",
      "Text": "Empyrean Apparatus"
    },
    "FlavourTextKey": {
      "RowIndex": 384,
      "TableName": "FlavourText",
      "Id": "UniqueChest3"
    },
    "MinLevel": 80,
    "ModsKeys": [
      {
        "RowIndex": 6362,
        "TableName": "Mods",
        "Id": "ChestSummonRaresUniqueChest3"
      },
      {
        "RowIndex": 6356,
        "TableName": "Mods",
        "Id": "ChestDropMapsUniqueUniqueChest3"
      },
      {
        "RowIndex": 6418,
        "TableName": "Mods",
        "Id": "ChestItemQualityUniqueChest3"
      },
      {
        "RowIndex": 6628,
        "TableName": "Mods",
        "Id": "UniqueChestNoRegularDrops"
      }
    ],
    "SpawnWeight": 40,
    "Unk006": [],
    "AOFile": "Metadata/Chests/StrongBoxes/MalachaisBox.ao",
    "Unk008": false,
    "Unk009": [],
    "AppearanceChestsKey": null,
    "ChestsKey": {
      "RowIndex": 87,
      "TableName": "Chests",
      "Id": "Metadata/Chests/StrongBoxes/CartographerEndMaps"
    },
    "Unk012": [
      {
        "RowIndex": 9179,
        "TableName": null
      }
    ]
  },
  {
    "RowIndex": 42,
    "Id": "BookStandUniqueBox",
    "WordsKey": {
      "RowIndex": 959,
      "TableName": "Words",
      "Text": "Book Stand Strongbox"
    },
    "FlavourTextKey": {
      "RowIndex": 665,
      "TableName": "FlavourText",
      "Id": "WIP"
    },
    "MinLevel": 0,
    "ModsKeys": [],
    "SpawnWeight": 0,
    "Unk006": [],
    "AOFile": "Metadata/Chests/StrongBoxes/BookStandStrongBox.ao",
    "Unk008": false,
    "Unk009": [],
    "AppearanceChestsKey": null,
    "ChestsKey": {
      "RowIndex": 100,
      "TableName": "Chests",
      "Id": "Metadata/Chests/StrongBoxes/StrongboxDivination"
    },
    "Unk012": []
  },
  {
    "RowIndex": 43,
    "Id": "VaalStrongboxSacrifice",
    "WordsKey": {
      "RowIndex": 1169,
      "TableName": "Words",
      "Text": "Reliquary of the Apex"
    },
    "FlavourTextKey": {
      "RowIndex": 2090,
      "TableName": "FlavourText",
      "Id": "UniqueChest13"
    },
    "MinLevel": 0,
    "ModsKeys": [
      {
        "RowIndex": 10372,
        "TableName": "Mods",
        "Id": "UniqueVaalStrongboxSacrificeDaemon_"
      }
    ],
    "SpawnWeight": 0,
    "Unk006": [],
    "AOFile": "Metadata/Chests/VaalChests/VaalGoldChest02.ao",
    "Unk008": true,
    "Unk009": [],
    "AppearanceChestsKey": null,
    "ChestsKey": {
      "RowIndex": 1185,
      "TableName": "Chests",
      "Id": "Metadata/Chests/StrongBoxes/OrnateVaalBoxSacrifice"
    },
    "Unk012": [
      {
        "RowIndex": 9179,
        "TableName": null
      }
    ]
  },
  {
    "RowIndex": 44,
    "Id": "VaalStrongboxMortal",
    "WordsKey": {
      "RowIndex": 1170,
      "TableName": "Words",
      "Text": "Reliquary of the Abyss"
    },
    "FlavourTextKey": {
      "RowIndex": 2091,
      "TableName": "FlavourText",
      "Id": "UniqueChest14"
    },
    "MinLevel": 0,
    "ModsKeys": [
      {
        "RowIndex": 10373,
        "TableName": "Mods",
        "Id": "UniqueVaalStrongboxMortalDaemon"
      }
    ],
    "SpawnWeight": 0,
    "Unk006": [],
    "AOFile": "Metadata/Chests/VaalChests/VaalGoldChest03.ao",
    "Unk008": true,
    "Unk009": [],
    "AppearanceChestsKey": null,
    "ChestsKey": {
      "RowIndex": 1186,
      "TableName": "Chests",
      "Id": "Metadata/Chests/StrongBoxes/OrnateVaalBoxMortal"
    },
    "Unk012": [
      {
        "RowIndex": 9179,
        "TableName": null
      }
    ]
  }
]